[
  { "level": "S", "name": "特別的蝴蝶妖精魅力服裝(男性用)", "probability": 0.0686 },
  { "level": "S", "name": "蝴蝶妖精魅力服裝(男性用)", "probability": 0.1373 },
  { "level": "S", "name": "特別的蝴蝶妖精自然服裝(男性用)", "probability": 0.0686 },
  { "level": "S", "name": "蝴蝶妖精自然服裝(男性用)", "probability": 0.1373 },
  { "level": "S", "name": "特別的蝴蝶妖精魅力服裝(女性用)", "probability": 0.0686 },
  { "level": "S", "name": "蝴蝶妖精魅力服裝(女性用)", "probability": 0.1373 },
  { "level": "S", "name": "特別的蝴蝶妖精自然服裝(女性用)", "probability": 0.0686 },
  { "level": "S", "name": "蝴蝶妖精自然服裝(女性用)", "probability": 0.1373 },
  { "level": "S", "name": "蝴蝶妖精手部裝飾(男性用)", "probability": 0.1647 },
  { "level": "S", "name": "蝴蝶妖精鞋子(男性用)", "probability": 0.1647 },
  { "level": "S", "name": "蝴蝶妖精假髮(男性用)", "probability": 0.1647 },
  { "level": "S", "name": "蝴蝶妖精鞋子(女性用)", "probability": 0.1647 },
  { "level": "S", "name": "蝴蝶妖精手部裝飾(女性用)", "probability": 0.1647 },
  { "level": "S", "name": "蝴蝶妖精假髮(女性用)", "probability": 0.1647 },
  { "level": "S", "name": "特別的蝴蝶妖精翅膀(魔力賦予)", "probability": 0.0137 },
  { "level": "S", "name": "優雅的蝴蝶妖精翅膀", "probability": 0.0275 },
  { "level": "S", "name": "高潔的蝴蝶妖精翅膀", "probability": 0.0275 },
  { "level": "S", "name": "璀璨的蝴蝶妖精翅膀", "probability": 0.0275 },
  { "level": "S", "name": "絢麗的蝴蝶妖精翅膀", "probability": 0.0275 },
  { "level": "S", "name": "蝴蝶妖精光環", "probability": 0.0412 },
  { "level": "S", "name": "夢幻之花第2稱號兌換券", "probability": 0.0824 },
  { "level": "S", "name": "夢幻之蝶第2稱號兌換券", "probability": 0.0824 },
  { "level": "S", "name": "特別的夢幻之花第2稱號兌換券", "probability": 0.0137 },
  { "level": "S", "name": "特別的夢幻之蝶第2稱號兌換卷", "probability": 0.0137 },
  { "level": "S", "name": "蝴蝶妖精劍外型卷軸", "probability": 0.0686 },
  { "level": "S", "name": "蝴蝶妖精魔導書", "probability": 0.0686 },
  { "level": "S", "name": "蝴蝶妖精眼罩(臉部裝飾欄位專用)", "probability": 0.1922 },
  { "level": "S", "name": "蝴蝶妖精耳環(臉部裝飾欄位專用)", "probability": 0.1922 },
  { "level": "S", "name": "特別灰暗繡球花水藍第2稱號兌換券", "probability": 0.0137 },
  { "level": "S", "name": "特別柔和繡球花水藍第2稱號兌換券", "probability": 0.0137 },
  { "level": "S", "name": "特別虛空蝴蝶第2稱號兌換卷", "probability": 0.0275 },
  { "level": "S", "name": "特別浪漫繡球花水藍第2稱號兌換券", "probability": 0.0275 },
  { "level": "S", "name": "特別死亡之手第2稱號兌換卷", "probability": 0.0412 },
  { "level": "S", "name": "教授J第2稱號兌換券", "probability": 0.2196 },
  { "level": "S", "name": "特別的實況Vtuber服裝(女性用)", "probability": 0.1373 },
  { "level": "S", "name": "實況Vtuber假髮(男性用)", "probability": 0.2471 },
  { "level": "S", "name": "實況Vtuber假髮(女性用)", "probability": 0.2471 },
  { "level": "S", "name": "實況Vtuber靴子(女性用)", "probability": 0.2471 },
  { "level": "S", "name": "實況Vtuber服裝(女性用)", "probability": 0.2471 },
  { "level": "S", "name": "實況Vtuber靴子(男性用)", "probability": 0.2471 },
  { "level": "S", "name": "實況Vtuber手套(女性用)", "probability": 0.2471 },
  { "level": "S", "name": "實況Vtuber手套(男性用)", "probability": 0.2471 },
  { "level": "S", "name": "特別的實況Vtuber服裝(男性用)", "probability": 0.1373 },
  { "level": "S", "name": "實況Vtuber服裝(男性用)", "probability": 0.2471 },
  { "level": "S", "name": "神獸的守護者星塵形象", "probability": 0.1373 },
  { "level": "S", "name": "淘氣風星塵的形象", "probability": 0.0686 },
  { "level": "S", "name": "王城魔法師星塵的形象", "probability": 0.0412 },
  { "level": "S", "name": "七尾狐星塵的形象", "probability": 0.0412 },
  { "level": "S", "name": "強襲抗暴軍無人機星塵的形象", "probability": 0.1373 },
  { "level": "S", "name": "強襲抗暴軍運送機星塵的形象", "probability": 0.1373 },
  { "level": "A", "name": "托爾維斯第二稱號獲得優惠券", "probability": 1.2904 },
  { "level": "A", "name": "艾薇琳第二稱號獲得優惠券", "probability": 1.2904 },
  { "level": "A", "name": "卡茲遠第二稱號獲得優惠券", "probability": 1.2904 },
  { "level": "A", "name": "寶藏獵人 第2稱號取得券", "probability": 1.3124 },
  { "level": "A", "name": "灰暗繡球花水藍第2稱號兌換券", "probability": 1.3124 },
  { "level": "A", "name": "諾亞達第2稱號取得券", "probability": 1.3124 },
  { "level": "A", "name": "柔和繡球花水藍第2稱號兌換券", "probability": 1.3124 },
  { "level": "A", "name": "浪漫繡球花水藍第2稱號兌換券", "probability": 1.3124 },
  { "level": "A", "name": "艾頓第2稱號取得券", "probability": 1.3124 },
  { "level": "A", "name": "梅林第2稱號取得券", "probability": 1.3124 },
  { "level": "A", "name": "小憤怒(特級)", "probability": 1.3124 },
  { "level": "A", "name": "黃金鐵鍊盔甲(特級)", "probability": 1.3124 },
  { "level": "A", "name": "魔法鍋(特級)", "probability": 1.3124 },
  { "level": "A", "name": "黃色標槍(特級)", "probability": 1.3124 },
  { "level": "A", "name": "盛開鬱金香的椅子", "probability": 1.3124 },
  { "level": "A", "name": "鬱金香椅子", "probability": 1.2904 },
  { "level": "A", "name": "鬱金香熱氣球", "probability": 1.3124 },
  { "level": "A", "name": "夢想家的烏雲床", "probability": 1.2904 },
  { "level": "A", "name": "藍莓火花光環", "probability": 1.2904 },
  { "level": "A", "name": "深海的魚缸", "probability": 1.2904 },
  { "level": "B", "name": "強而有力的第2稱號兌換券", "probability": 1.3014 },
  { "level": "B", "name": "洛維林第二稱號獲得優惠券", "probability": 1.3014 },
  { "level": "B", "name": "極弱的第2稱號兌換券", "probability": 1.3014 },
  { "level": "B", "name": "連續技:狂暴拳擊技能修練藥水", "probability": 1.3453 },
  { "level": "B", "name": "蜘蛛網射擊技能修練藥水", "probability": 1.3453 },
  { "level": "B", "name": "狂暴化技能修練藥水", "probability": 1.3453 },
  { "level": "B", "name": "連續技能: 螺旋勾拳修練藥水", "probability": 1.3453 },
  { "level": "B", "name": "連續技能: 導電拳擊修練藥水", "probability": 1.3453 },
  { "level": "B", "name": "髮型指定染色劑箱子:巧克力色#623022", "probability": 1.3453 },
  { "level": "B", "name": "髮型指定染色劑箱子:金黃色#DC9C34", "probability": 1.3453 },
  { "level": "B", "name": "髮型指定染色劑箱子:銀銅色#EFEAB5", "probability": 1.3453 },
  { "level": "B", "name": "髮型指定染色劑:巴雷斯深天空色#2881DD", "probability": 1.3453 },
  { "level": "B", "name": "髮型指定染色劑箱子:巴雷斯淺天藍色#B9EEFF", "probability": 1.3453 },
  { "level": "B", "name": "雙手劍, 雙手劍, 刺劍動作卡片(60日)", "probability": 1.3453 },
  { "level": "B", "name": "法利亞斯之雨", "probability": 1.3453 },
  { "level": "B", "name": "法利亞斯之露", "probability": 1.3453 },
  { "level": "B", "name": "紫光稜鏡箱子", "probability": 1.3453 },
  { "level": "B", "name": "單色組合-櫻花粉紅", "probability": 1.3453 },
  { "level": "B", "name": "3段玫瑰花盆2個", "probability": 1.3453 },
  { "level": "B", "name": "單色組合-戀愛粉紅", "probability": 1.3453 },
  { "level": "B", "name": "法利亞斯的瀑布", "probability": 1.3453 },
  { "level": "B", "name": "神聖光之魔法書", "probability": 1.3453 },
  { "level": "B", "name": "梅樂的調音器", "probability": 1.3453 },
  { "level": "B", "name": "才能技能時空膠囊", "probability": 1.3453 },
  { "level": "B", "name": "單色組合-魅力紫", "probability": 1.3453 },
  { "level": "B", "name": "2段玫瑰花盆2個", "probability": 1.3453 },
  { "level": "C", "name": "南瓜迷你寵物", "probability": 1.3838 },
  { "level": "C", "name": "蝙蝠王冠 (女性用)", "probability": 1.3838 },
  { "level": "C", "name": "蝙蝠王冠 (男性用)", "probability": 1.3838 },
  { "level": "C", "name": "冰雪王冠 (女性專用)", "probability": 1.3838 },
  { "level": "C", "name": "冰雪王冠 (男性專用)", "probability": 1.3838 },
  { "level": "C", "name": "克莉絲應援扇(經驗值 550%)", "probability": 1.3838 },
  { "level": "C", "name": "梅樂的調音器(夥伴用)", "probability": 1.3838 },
  { "level": "C", "name": "艾爾拉哈手指娃娃", "probability": 1.3838 },
  { "level": "C", "name": "香橙長袍", "probability": 1.3838 },
  { "level": "C", "name": "安德拉絲手指娃娃", "probability": 1.3838 },
  { "level": "C", "name": "旭日東昇石板", "probability": 1.3838 },
  { "level": "C", "name": "娜歐應援扇", "probability": 1.3838 },
  { "level": "C", "name": "娜歐頭飾", "probability": 1.3838 },
  { "level": "C", "name": "烈焰見習騎士團任務水晶(2倍)(可以交易)5個", "probability": 1.3838 },
  { "level": "C", "name": "馴鹿長袍", "probability": 1.3838 },
  { "level": "C", "name": "錫古手指娃娃", "probability": 1.3838 },
  { "level": "C", "name": "潘應援扇(探險經驗值 8萬)", "probability": 1.3838 },
  { "level": "C", "name": "魔法施展速度增加藥水 (30分鐘)", "probability": 1.3838 },
  { "level": "C", "name": "佛格斯應援扇(經驗值550%)", "probability": 1.3838 },
  { "level": "C", "name": "露娜應援扇(探險經驗值 8萬)", "probability": 1.3838 },
  { "level": "C", "name": "寵物染劑", "probability": 1.3838 },
  { "level": "C", "name": "潘手指娃娃", "probability": 1.3838 },
  { "level": "C", "name": "茉麗安手指娃娃", "probability": 1.3838 },
  { "level": "C", "name": "弩動作卡片(60日) 兌換券", "probability": 1.3838 }
]
